minatar/__init__.py
minatar/environment.py
minatar/gui.py
minatar/gym.py
minatar/environments/__init__.py
minatar/environments/asterix.py
minatar/environments/breakout.py
minatar/environments/freeway.py
minatar/environments/seaquest.py
minatar/environments/space_invaders.py
MinAtar-1.0.15.dist-info/METADATA
MinAtar-1.0.15.dist-info/WHEEL
MinAtar-1.0.15.dist-info/entry_points.txt
MinAtar-1.0.15.dist-info/top_level.txt
MinAtar-1.0.15.dist-info/RECORD
